camrcs.py
camrcs-0.8.0.dist-info/METADATA
camrcs-0.8.0.dist-info/WHEEL
camrcs-0.8.0.dist-info/entry_points.txt
camrcs-0.8.0.dist-info/top_level.txt
camrcs-0.8.0.dist-info/RECORD
