Metadata-Version: 2.1
Name: camrcs
Version: 0.8.0
Summary: A package for management of Cambridge Research Cold Storage backups
Author: Niek Wit
Author-email: nw416@cam.ac.uk
License: MIT
Project-URL: Documentation, https://camrcs.readthedocs.io
Project-URL: Source, https://github.com/niekwit/camrcs
Classifier: Development Status :: 4 - Beta
Classifier: Intended Audience :: Science/Research
Classifier: License :: OSI Approved :: MIT License
Classifier: Operating System :: POSIX :: Linux
Classifier: Programming Language :: Python :: 3
Classifier: Topic :: System :: Archiving :: Backup
Requires-Dist: pandas
Requires-Dist: Click
Requires-Dist: numpy
